{"data":[{"author":"calamari Software","capabilities":[],"category_id":"5261a8fb3b773043d5000012","category_name":"Games","category_color":"b57ad3","changelog":[{"version":"1.0.0","published_date":"2014-08-01T06:09:21.182Z","release_notes":"Initial release"}],"companions":{"ios":null,"android":null},"compatibility":{"ios":{"supported":true,"min_js_version":-1},"android":{"supported":true},"aplite":{"supported":true,"firmware":{"major":2}},"basalt":{"supported":true,"firmware":{"major":3}},"chalk":{"supported":false,"firmware":{"major":3}},"diorite":{"supported":true,"firmware":{"major":3}},"emery":{"supported":true,"firmware":{"major":3}}},"created_at":"2014-08-01T06:03:22.079Z","description":"Klondike Solitaire for Pebble.\r\n\r\nIncludes Vegas scoring, one and three card draw modes, and selectable flip limit. Controls allow you to automatically skip over ineligible piles and move cards to the foundations, for more fun and less button presses! \r\n\r\nPlease visit the webpage to report bugs and download the source code.\r\n\r\nEnjoy!","developer_id":"53cb0606f87b113d8700000d","header_images":[{"orig":"https://assets.getpebble.com/api/file/5pRhgOXCQcCn2qwGiLSD/convert?cache=true&fit=crop","720x320":"https://assets.getpebble.com/api/file/5pRhgOXCQcCn2qwGiLSD/convert?cache=true&fit=crop&w=720&h=320"}],"hearts":125,"icon_image":{"28x28":"https://assets.getpebble.com/api/file/q5MfM5A6RdaBsnVkjH5O/convert?cache=true&fit=crop&w=28&h=28","48x48":"https://assets.getpebble.com/api/file/q5MfM5A6RdaBsnVkjH5O/convert?cache=true&fit=crop&w=48&h=48"},"id":"53db2daae4fa76655c000077","latest_release":{"id":"53db2eb8e4fa76f6710000ec","js_version":-1,"pbw_file":"https://www.filepicker.io/api/file/VoIC3jhPSmKzm2PUC6pA","published_date":"2014-08-01T06:09:21.182Z","release_notes":"Initial release","version":"1.0.0"},"links":{"add":"https://dev-portal.getpebble.com/api/applications/53db2daae4fa76655c000077/add","remove":"https://dev-portal.getpebble.com/api/applications/53db2daae4fa76655c000077/remove","add_heart":"https://dev-portal.getpebble.com/api/applications/53db2daae4fa76655c000077/add_heart","remove_heart":"https://dev-portal.getpebble.com/api/applications/53db2daae4fa76655c000077/remove_heart","add_flag":"https://dev-portal.getpebble.com/api/applications/53db2daae4fa76655c000077/flags/add","remove_flag":"https://dev-portal.getpebble.com/api/applications/53db2daae4fa76655c000077/flags/remove","share":"https://apps.getpebble.com/applications/53db2daae4fa76655c000077"},"list_image":{"80x80":"https://assets.getpebble.com/api/file/ynUdSrmERaOupuhBpbd8/convert?cache=true&fit=crop&w=80&h=80","144x144":"https://assets.getpebble.com/api/file/ynUdSrmERaOupuhBpbd8/convert?cache=true&fit=crop&w=144&h=144"},"published_date":"2014-08-01T06:09:37.619Z","screenshot_hardware":"aplite","screenshot_images":[{"144x168":"https://assets.getpebble.com/api/file/fEKEAAi2SGGYhj0w09sY/convert?cache=true&fit=crop&w=144&h=168"},{"144x168":"https://assets.getpebble.com/api/file/02fw7MrdSK241fCrIs3G/convert?cache=true&fit=crop&w=144&h=168"},{"144x168":"https://assets.getpebble.com/api/file/Ai1cATRVRbPr8LaipTJJ/convert?cache=true&fit=crop&w=144&h=168"}],"source":"http://code.google.com/p/pebble-solitaire/source/browse/","title":"Solitaire","type":"watchapp","uuid":"f8043138-6757-416c-91ad-fb7d85f35abe","website":"http://code.google.com/p/pebble-solitaire/"}],"limit":20,"offset":0,"links":{"nextPage":null}}