{"author": "EpicLaith", "capabilities": [], "category_id": "528d3ef2dc7b5f580700000a", "category_name": "Faces", "category_color": "ffffff", "changelog": [{"version": "1.0.0", "published_date": "2014-08-06T07:43:09.963Z", "release_notes": "Mustang Eleanor "}], "companions": {"ios": null, "android": null}, "compatibility": {"ios": {"supported": true, "min_js_version": -1}, "android": {"supported": true}, "aplite": {"supported": true, "firmware": {"major": 2}}, "basalt": {"supported": true, "firmware": {"major": 3}}, "chalk": {"supported": false, "firmware": {"major": 3}}, "diorite": {"supported": true, "firmware": {"major": 3}}, "emery": {"supported": true, "firmware": {"major": 3}}}, "created_at": "2014-08-06T07:41:35.483Z", "description": "My favourite mustang, now its on my wrist! Download this custom watchface now for free! \r\nSupport my work on Patreon please below on the source URL :) \r\n\r\n", "developer_id": "53cbf761d7238308ee000062", "hearts": 8, "id": "53e1dc2f93b6b68b5f000064", "latest_release": {"id": "53e1dc866ad27e10e0000001", "js_version": -1, "pbw_file": "https://www.filepicker.io/api/file/q2O4F0PJQxOAGxm4D1yB", "published_date": "2014-08-06T07:43:09.963Z", "release_notes": "Mustang Eleanor ", "version": "1.0.0"}, "links": {"add": "https://dev-portal.getpebble.com/api/applications/53e1dc2f93b6b68b5f000064/add", "remove": "https://dev-portal.getpebble.com/api/applications/53e1dc2f93b6b68b5f000064/remove", "add_heart": "https://dev-portal.getpebble.com/api/applications/53e1dc2f93b6b68b5f000064/add_heart", "remove_heart": "https://dev-portal.getpebble.com/api/applications/53e1dc2f93b6b68b5f000064/remove_heart", "add_flag": "https://dev-portal.getpebble.com/api/applications/53e1dc2f93b6b68b5f000064/flags/add", "remove_flag": "https://dev-portal.getpebble.com/api/applications/53e1dc2f93b6b68b5f000064/flags/remove", "share": "https://apps.getpebble.com/applications/53e1dc2f93b6b68b5f000064"}, "list_image": {"80x80": "https://assets.getpebble.com/api/file/JvHqOycgSB2Bp4Lb6TDW/convert?cache=true&fit=crop&w=80&h=80", "144x144": "https://assets.getpebble.com/api/file/JvHqOycgSB2Bp4Lb6TDW/convert?cache=true&fit=crop&w=144&h=144"}, "published_date": "2014-08-06T07:43:14.628Z", "screenshot_hardware": "aplite", "screenshot_images": [{"144x168": "https://assets.getpebble.com/api/file/JvHqOycgSB2Bp4Lb6TDW/convert?cache=true&fit=crop&w=144&h=168"}], "source": "http://www.patreon.com/user?u=254358", "title": "Mustang Eleanor", "type": "watchface", "uuid": "13371337-f36b-429f-a79f-594534f5e182", "website": ""}