{"author": "Zeitaku Apps Limited", "capabilities": [], "category_id": "5261a8fb3b773043d500000f", "category_name": "Tools & Utilities", "category_color": "fdbf37", "changelog": [{"version": "1.0", "published_date": "2014-11-12T06:32:18.097Z", "release_notes": ""}], "companions": {"ios": {"id": "5476baf067c622c935000005", "icon": "https://www.filepicker.io/api/file/nlkMFFLQRee56yUxPRrM", "name": "PebbSpeed FREE-Speed Limit Alert System and Wrist Speedometer for Pebble Smartwatch", "url": "http://appstore.com/pebbspeedfreespeedlimitalertsystemandwristspeedometerforpebblesmartwatch", "required": true, "pebblekit_version": "2"}, "android": null}, "compatibility": {"ios": {"supported": true, "min_js_version": -1}, "android": {"supported": false}, "aplite": {"supported": true, "firmware": {"major": 2}}, "basalt": {"supported": true, "firmware": {"major": 3}}, "chalk": {"supported": false, "firmware": {"major": 3}}, "diorite": {"supported": true, "firmware": {"major": 3}}, "emery": {"supported": true, "firmware": {"major": 3}}}, "created_at": "2014-11-12T05:12:27.651Z", "description": "Do you have a problem speeding in school zones? How about while in a rush driving somewhere for work? This app is also excellent for mechanics and people that own vehicles with broken speedometers. Give it a shot guys you won't be disappointed!", "developer_id": "52dfa641011368390d00007a", "header_images": [{"orig": "https://assets.getpebble.com/api/file/EQXc2pBDTk2u296dCISy/convert?cache=true&fit=crop", "720x320": "https://assets.getpebble.com/api/file/EQXc2pBDTk2u296dCISy/convert?cache=true&fit=crop&w=720&h=320"}, {"orig": "https://assets.getpebble.com/api/file/mrTd6dRVOd7R8iJLvfiw/convert?cache=true&fit=crop", "720x320": "https://assets.getpebble.com/api/file/mrTd6dRVOd7R8iJLvfiw/convert?cache=true&fit=crop&w=720&h=320"}, {"orig": "https://assets.getpebble.com/api/file/hghA3IdpRGSe9yMLdCRY/convert?cache=true&fit=crop", "720x320": "https://assets.getpebble.com/api/file/hghA3IdpRGSe9yMLdCRY/convert?cache=true&fit=crop&w=720&h=320"}], "hearts": 73, "icon_image": {"28x28": "https://assets.getpebble.com/api/file/qe9Lk0woS9Pq6ETqJ5T1/convert?cache=true&fit=crop&w=28&h=28", "48x48": "https://assets.getpebble.com/api/file/qe9Lk0woS9Pq6ETqJ5T1/convert?cache=true&fit=crop&w=48&h=48"}, "id": "5462ec3b6c89602426000017", "latest_release": {"id": "5462feea6c8960a8e8000029", "js_version": -1, "pbw_file": "https://www.filepicker.io/api/file/2oY7tjIRSAGoCgKthcXC", "published_date": "2014-11-12T06:32:18.097Z", "release_notes": "", "version": "1.0"}, "links": {"add": "https://dev-portal.getpebble.com/api/applications/5462ec3b6c89602426000017/add", "remove": "https://dev-portal.getpebble.com/api/applications/5462ec3b6c89602426000017/remove", "add_heart": "https://dev-portal.getpebble.com/api/applications/5462ec3b6c89602426000017/add_heart", "remove_heart": "https://dev-portal.getpebble.com/api/applications/5462ec3b6c89602426000017/remove_heart", "add_flag": "https://dev-portal.getpebble.com/api/applications/5462ec3b6c89602426000017/flags/add", "remove_flag": "https://dev-portal.getpebble.com/api/applications/5462ec3b6c89602426000017/flags/remove", "share": "https://apps.getpebble.com/applications/5462ec3b6c89602426000017"}, "list_image": {"80x80": "https://assets.getpebble.com/api/file/hB2rdDwQfqP5Y8IAVGq2/convert?cache=true&fit=crop&w=80&h=80", "144x144": "https://assets.getpebble.com/api/file/hB2rdDwQfqP5Y8IAVGq2/convert?cache=true&fit=crop&w=144&h=144"}, "published_date": "2015-12-15T13:18:38.711Z", "screenshot_hardware": "aplite", "screenshot_images": [{"144x168": "https://assets.getpebble.com/api/file/pPZSrcpiShyqh77gOOks/convert?cache=true&fit=crop&w=144&h=168"}, {"144x168": "https://assets.getpebble.com/api/file/6oLEnjNaTGawF7iSYSeJ/convert?cache=true&fit=crop&w=144&h=168"}], "source": "", "title": "PebbSpeed FREE-SPEEDOMETER AND SPEED LIMIT ALERT ON YOUR WRIST", "type": "watchapp", "uuid": "064f3867-8021-4b56-aaa5-b8a2c45c6993", "website": ""}