{"author": "rm.dev", "capabilities": [], "category_id": "528d3ef2dc7b5f580700000a", "category_name": "Faces", "category_color": "ffffff", "changelog": [{"version": "1.2", "published_date": "2015-12-03T14:09:14.232Z", "release_notes": "Disabled console log."}, {"version": "1.1", "published_date": "2015-12-02T11:12:19.166Z", "release_notes": "Lots of changes to allow the interface to be different colours. Configuration for text and line colours, background on/off, month-date order, speeding up the boot animation.\r\nAlso version for Aplite, which doesn't have a loading animation or thick interface lines because Pebble never got around to porting SDK3 for Aplite so no support for sequence animations or stroke width."}, {"version": "1.0", "published_date": "2015-11-29T21:50:44.114Z", "release_notes": "Initial release!"}], "companions": {"ios": null, "android": null}, "compatibility": {"ios": {"supported": true, "min_js_version": -1}, "android": {"supported": true}, "aplite": {"supported": true, "firmware": {"major": 2}}, "basalt": {"supported": true, "firmware": {"major": 3}}, "chalk": {"supported": false, "firmware": {"major": 3}}, "diorite": {"supported": true, "firmware": {"major": 3}}, "emery": {"supported": true, "firmware": {"major": 3}}}, "created_at": "2015-11-29T21:09:19.409Z", "description": "Looking for your very own Pip-Boy? Sorry, your Pebble is way too small and svelte - but this might be the next best thing. In celebration of Fallout 4 here's a watchface crafted as a loving tribute to FO4 with loading screen to give you your Fallout fix when you're away from home.\r\n\r\nNow with configuration of colours, background, and month/day order, and glowing Pip-Boy effect when charging! Phew!", "developer_id": "52c5b9ad11bc0391eb000056", "header_images": "", "hearts": 352, "id": "565b697ff4b2741a7f0000c9", "latest_release": {"id": "565ef84398ed181802000031", "js_md5": "8761789b4da403a81ac64fe49f80b41a", "js_version": -1, "pbw_file": "https://www.filepicker.io/api/file/b4mfWNDRLWZMjvrIQGl6", "published_date": "2015-12-03T14:09:14.232Z", "release_notes": "Disabled console log.", "version": "1.2"}, "links": {"add": "https://dev-portal.getpebble.com/api/applications/565b697ff4b2741a7f0000c9/add", "remove": "https://dev-portal.getpebble.com/api/applications/565b697ff4b2741a7f0000c9/remove", "add_heart": "https://dev-portal.getpebble.com/api/applications/565b697ff4b2741a7f0000c9/add_heart", "remove_heart": "https://dev-portal.getpebble.com/api/applications/565b697ff4b2741a7f0000c9/remove_heart", "add_flag": "https://dev-portal.getpebble.com/api/applications/565b697ff4b2741a7f0000c9/flags/add", "remove_flag": "https://dev-portal.getpebble.com/api/applications/565b697ff4b2741a7f0000c9/flags/remove", "share": "https://apps.getpebble.com/applications/565b697ff4b2741a7f0000c9"}, "list_image": {"80x80": "https://assets.getpebble.com/api/file/ceh4FekXQPW27sz0rbEk/convert?cache=true&fit=crop&w=80&h=80", "144x144": "https://assets.getpebble.com/api/file/ceh4FekXQPW27sz0rbEk/convert?cache=true&fit=crop&w=144&h=144"}, "published_date": "2015-12-02T11:24:14.626Z", "screenshot_hardware": "basalt", "screenshot_images": [{"144x168": "https://assets.getpebble.com/api/file/ceh4FekXQPW27sz0rbEk/convert?cache=true&fit=crop&w=144&h=168"}], "source": "", "title": "Pip-pip", "type": "watchface", "uuid": "0e988a35-af01-4c92-8b2b-d4322205dc06", "website": ""}