{"data":[{"author":"Killerpokemon","capabilities":[],"category_id":"528d3ef2dc7b5f580700000a","category_name":"Faces","category_color":"ffffff","changelog":[{"version":"1.0","published_date":"2015-07-12T20:38:32.789Z","release_notes":"This is my very first (Posted) Pebble Watch face. It has the date, time, and day of the week, Bluetooth, and Battery indicators on it, along with the MSI Logo. I hope you like it!"}],"companions":{"ios":null,"android":null},"compatibility":{"ios":{"supported":true,"min_js_version":-1},"android":{"supported":true},"aplite":{"supported":true,"firmware":{"major":2}},"basalt":{"supported":true,"firmware":{"major":3}},"chalk":{"supported":false,"firmware":{"major":3}},"diorite":{"supported":true,"firmware":{"major":3}},"emery":{"supported":true,"firmware":{"major":3}}},"created_at":"2015-07-12T20:28:05.969Z","description":"This is my first Posted Pebble Watchface. I hope you like it!","developer_id":"54f4e9e526cc32801f0000a0","header_images":"","hearts":4,"id":"55a2cdd5c643f9e9de000052","latest_release":{"id":"55a2ceade71e033ec0000068","js_version":-1,"pbw_file":"https://www.filepicker.io/api/file/oq7vC8sR5iTlYpeLQRMg","published_date":"2015-07-12T20:38:32.789Z","release_notes":"This is my very first (Posted) Pebble Watch face. It has the date, time, and day of the week, Bluetooth, and Battery indicators on it, along with the MSI Logo. I hope you like it!","version":"1.0"},"links":{"add":"https://dev-portal.getpebble.com/api/applications/55a2cdd5c643f9e9de000052/add","remove":"https://dev-portal.getpebble.com/api/applications/55a2cdd5c643f9e9de000052/remove","add_heart":"https://dev-portal.getpebble.com/api/applications/55a2cdd5c643f9e9de000052/add_heart","remove_heart":"https://dev-portal.getpebble.com/api/applications/55a2cdd5c643f9e9de000052/remove_heart","add_flag":"https://dev-portal.getpebble.com/api/applications/55a2cdd5c643f9e9de000052/flags/add","remove_flag":"https://dev-portal.getpebble.com/api/applications/55a2cdd5c643f9e9de000052/flags/remove","share":"https://apps.getpebble.com/applications/55a2cdd5c643f9e9de000052"},"list_image":{"80x80":"https://assets.getpebble.com/api/file/j5ErXlhwTWCjQvLhRJpl/convert?cache=true&fit=crop&w=80&h=80","144x144":"https://assets.getpebble.com/api/file/j5ErXlhwTWCjQvLhRJpl/convert?cache=true&fit=crop&w=144&h=144"},"published_date":"2015-07-12T20:38:58.797Z","screenshot_hardware":"aplite","screenshot_images":[{"144x168":"https://assets.getpebble.com/api/file/j5ErXlhwTWCjQvLhRJpl/convert?cache=true&fit=crop&w=144&h=168"}],"source":"http://www.watchface-generator.de/wf/20150712/msi_watchface/","title":"Msi Watchface","type":"watchface","uuid":"13371337-c7a8-4cd9-ad7f-9867120a7e23","website":"http://d16577.wix.com/danielgrub"}],"limit":20,"offset":0,"links":{"nextPage":null}}