{"data":[{"author":"MartialElch","capabilities":[],"category_id":"528d3ef2dc7b5f580700000a","category_name":"Faces","category_color":"ffffff","changelog":[{"version":"1.4","published_date":"2015-05-18T15:58:03.665Z","release_notes":"1.4\r\n- add invert option to have a white background with black numbers and tickmarks\r\n- draw the watch hands instead of using bitmaps\r\n"},{"version":"1.3","published_date":"2015-05-12T18:43:12.035Z","release_notes":"- fix seconds hand\r\n  watch hand was not hidden when changing the watch face and returning to Aviator 24h"},{"version":"1.2","published_date":"2015-05-12T18:43:01.231Z","release_notes":""}],"companions":{"ios":null,"android":null},"compatibility":{"ios":{"supported":true,"min_js_version":-1},"android":{"supported":true},"aplite":{"supported":true,"firmware":{"major":2}},"basalt":{"supported":true,"firmware":{"major":3}},"chalk":{"supported":false,"firmware":{"major":3}},"diorite":{"supported":true,"firmware":{"major":3}},"emery":{"supported":true,"firmware":{"major":3}}},"created_at":"2015-05-08T14:23:01.441Z","description":"Pilots watchface with 24h dial.","developer_id":"552d74770835230eb000005d","header_images":"","hearts":59,"id":"554cc6c5b62c11889b000053","latest_release":{"id":"555a0bed9b053800fa0000d4","js_md5":"3b0cfda36131fdeee5f90d1d5ac6d72d","js_version":-1,"pbw_file":"https://www.filepicker.io/api/file/MgIBpw17RVGEyOMJGpcr","published_date":"2015-05-18T15:58:03.665Z","release_notes":"1.4\r\n- add invert option to have a white background with black numbers and tickmarks\r\n- draw the watch hands instead of using bitmaps\r\n","version":"1.4"},"links":{"add":"https://dev-portal.getpebble.com/api/applications/554cc6c5b62c11889b000053/add","remove":"https://dev-portal.getpebble.com/api/applications/554cc6c5b62c11889b000053/remove","add_heart":"https://dev-portal.getpebble.com/api/applications/554cc6c5b62c11889b000053/add_heart","remove_heart":"https://dev-portal.getpebble.com/api/applications/554cc6c5b62c11889b000053/remove_heart","add_flag":"https://dev-portal.getpebble.com/api/applications/554cc6c5b62c11889b000053/flags/add","remove_flag":"https://dev-portal.getpebble.com/api/applications/554cc6c5b62c11889b000053/flags/remove","share":"https://apps.getpebble.com/applications/554cc6c5b62c11889b000053"},"list_image":{"80x80":"https://assets.getpebble.com/api/file/aIQyLs3wSdG1WBHm0PJU/convert?cache=true&fit=crop&w=80&h=80","144x144":"https://assets.getpebble.com/api/file/aIQyLs3wSdG1WBHm0PJU/convert?cache=true&fit=crop&w=144&h=144"},"published_date":"2015-05-08T14:29:58.622Z","screenshot_hardware":"aplite","screenshot_images":[{"144x168":"https://assets.getpebble.com/api/file/aIQyLs3wSdG1WBHm0PJU/convert?cache=true&fit=crop&w=144&h=168"},{"144x168":"https://assets.getpebble.com/api/file/Gyy48xbTdmEse2ipmvD2/convert?cache=true&fit=crop&w=144&h=168"}],"source":"https://github.com/MartialElch/PebbleAviator24hWatch.git","title":"Aviator 24h","type":"watchface","uuid":"0a1a7a13-d798-4067-ad0f-6cda4cd9b158","website":""}],"limit":20,"offset":0,"links":{"nextPage":null}}