{"author": "William", "capabilities": [], "category_id": "528d3ef2dc7b5f580700000a", "category_name": "Faces", "category_color": "ffffff", "changelog": [{"version": "1.0", "published_date": "2014-12-08T03:16:26.794Z", "release_notes": ""}], "companions": {"ios": null, "android": null}, "compatibility": {"ios": {"supported": true, "min_js_version": -1}, "android": {"supported": true}, "aplite": {"supported": true, "firmware": {"major": 2}}, "basalt": {"supported": true, "firmware": {"major": 3}}, "chalk": {"supported": false, "firmware": {"major": 3}}, "diorite": {"supported": true, "firmware": {"major": 3}}, "emery": {"supported": true, "firmware": {"major": 3}}}, "created_at": "2014-12-08T03:15:22.254Z", "description": "Rihanna LOVE", "developer_id": "547be0ee4fa17fff250000c3", "hearts": 6, "id": "548517cac3c85c7b70000108", "latest_release": {"id": "548518024fe779b735000015", "js_version": -1, "pbw_file": "https://www.filepicker.io/api/file/XEx0NoA7SESlmAoj05bA", "published_date": "2014-12-08T03:16:26.794Z", "release_notes": "", "version": "1.0"}, "links": {"add": "https://dev-portal.getpebble.com/api/applications/548517cac3c85c7b70000108/add", "remove": "https://dev-portal.getpebble.com/api/applications/548517cac3c85c7b70000108/remove", "add_heart": "https://dev-portal.getpebble.com/api/applications/548517cac3c85c7b70000108/add_heart", "remove_heart": "https://dev-portal.getpebble.com/api/applications/548517cac3c85c7b70000108/remove_heart", "add_flag": "https://dev-portal.getpebble.com/api/applications/548517cac3c85c7b70000108/flags/add", "remove_flag": "https://dev-portal.getpebble.com/api/applications/548517cac3c85c7b70000108/flags/remove", "share": "https://apps.getpebble.com/applications/548517cac3c85c7b70000108"}, "list_image": {"80x80": "https://assets.getpebble.com/api/file/uBRPOzHSTOigxeznA5tP/convert?cache=true&fit=crop&w=80&h=80", "144x144": "https://assets.getpebble.com/api/file/uBRPOzHSTOigxeznA5tP/convert?cache=true&fit=crop&w=144&h=144"}, "published_date": "2014-12-08T03:16:40.260Z", "screenshot_hardware": "aplite", "screenshot_images": [{"144x168": "https://assets.getpebble.com/api/file/uBRPOzHSTOigxeznA5tP/convert?cache=true&fit=crop&w=144&h=168"}], "source": "", "title": "love Rihanna", "type": "watchface", "uuid": "13371337-691e-43be-a8be-5d75f59da78c", "website": ""}