{"data":[{"author":"Cermit","capabilities":[],"category_id":"528d3ef2dc7b5f580700000a","category_name":"Faces","category_color":"ffffff","changelog":[{"version":"1.1","published_date":"2015-10-16T17:05:42.915Z","release_notes":"Thiner Lines\r\nSome Bug Fixes"},{"version":"1.0","published_date":"2015-03-09T20:46:41.543Z","release_notes":""}],"companions":{"ios":null,"android":null},"compatibility":{"ios":{"supported":true,"min_js_version":27},"android":{"supported":true},"aplite":{"supported":true,"firmware":{"major":2}},"basalt":{"supported":true,"firmware":{"major":3}},"chalk":{"supported":false,"firmware":{"major":3}},"diorite":{"supported":true,"firmware":{"major":3}},"emery":{"supported":true,"firmware":{"major":3}}},"created_at":"2015-03-09T20:25:36.730Z","description":"Because of the many people who want this, here is the dark version of my Digital Clock.\r\nSoon i will release the original watchface with settings for that. This one is just to bridge the time till im ready with the original.","developer_id":"537b2637741b73e2f30000db","header_images":"","hearts":15,"id":"54fe01c08ab51e42b3000044","latest_release":{"id":"56212dcf768e7a75f900009c","js_md5":"3876dc2b86265ca56e78defad8d7840b","js_version":27,"pbw_file":"https://www.filepicker.io/api/file/6sQOe15ZTrmlq32GpQlc","published_date":"2015-10-16T17:05:42.915Z","release_notes":"Thiner Lines\r\nSome Bug Fixes","version":"1.1"},"links":{"add":"https://dev-portal.getpebble.com/api/applications/54fe01c08ab51e42b3000044/add","remove":"https://dev-portal.getpebble.com/api/applications/54fe01c08ab51e42b3000044/remove","add_heart":"https://dev-portal.getpebble.com/api/applications/54fe01c08ab51e42b3000044/add_heart","remove_heart":"https://dev-portal.getpebble.com/api/applications/54fe01c08ab51e42b3000044/remove_heart","add_flag":"https://dev-portal.getpebble.com/api/applications/54fe01c08ab51e42b3000044/flags/add","remove_flag":"https://dev-portal.getpebble.com/api/applications/54fe01c08ab51e42b3000044/flags/remove","share":"https://apps.getpebble.com/applications/54fe01c08ab51e42b3000044"},"list_image":{"80x80":"https://assets.getpebble.com/api/file/HDECfipKQuOq829MhzyL/convert?cache=true&fit=crop&w=80&h=80","144x144":"https://assets.getpebble.com/api/file/HDECfipKQuOq829MhzyL/convert?cache=true&fit=crop&w=144&h=144"},"published_date":"2015-03-09T20:47:20.660Z","screenshot_hardware":"aplite","screenshot_images":[{"144x168":"https://assets.getpebble.com/api/file/HDECfipKQuOq829MhzyL/convert?cache=true&fit=crop&w=144&h=168"}],"source":"","title":"Digital Clock Dark","type":"watchface","uuid":"6a8ae1a4-764b-4da7-85db-70b3a13755fb","website":""}],"limit":20,"offset":0,"links":{"nextPage":null}}