{"author": "F\u0131rat", "capabilities": [], "category_id": "528d3ef2dc7b5f580700000a", "category_name": "Faces", "category_color": "ffffff", "changelog": [{"version": "1.0", "published_date": "2016-11-03T14:12:44.124Z", "release_notes": ""}], "companions": {"ios": null, "android": null}, "compatibility": {"ios": {"supported": true, "min_js_version": -1}, "android": {"supported": true}, "aplite": {"supported": true, "firmware": {"major": 2}}, "basalt": {"supported": true, "firmware": {"major": 3}}, "chalk": {"supported": false, "firmware": {"major": 3}}, "diorite": {"supported": true, "firmware": {"major": 3}}, "emery": {"supported": true, "firmware": {"major": 3}}}, "created_at": "2016-11-03T14:09:28.380Z", "description": "b/w with date", "developer_id": "57fa3539937d4e95de000057", "header_images": "", "hearts": 3, "id": "581b45189cbbaf5d82000028", "latest_release": {"id": "581b45ce1c0888b9c300001e", "js_version": -1, "pbw_file": "https://www.filepicker.io/api/file/8wTZEv5MSImBoQozdEgg", "published_date": "2016-11-03T14:12:44.124Z", "release_notes": "", "version": "1.0"}, "links": {"add": "https://dev-portal.getpebble.com/api/applications/581b45189cbbaf5d82000028/add", "remove": "https://dev-portal.getpebble.com/api/applications/581b45189cbbaf5d82000028/remove", "add_heart": "https://dev-portal.getpebble.com/api/applications/581b45189cbbaf5d82000028/add_heart", "remove_heart": "https://dev-portal.getpebble.com/api/applications/581b45189cbbaf5d82000028/remove_heart", "add_flag": "https://dev-portal.getpebble.com/api/applications/581b45189cbbaf5d82000028/flags/add", "remove_flag": "https://dev-portal.getpebble.com/api/applications/581b45189cbbaf5d82000028/flags/remove", "share": "https://apps.getpebble.com/applications/581b45189cbbaf5d82000028"}, "list_image": {"80x80": "https://assets.getpebble.com/api/file/Ptij6mA6SbKDsyCjkcQM/convert?cache=true&fit=crop&w=80&h=80", "144x144": "https://assets.getpebble.com/api/file/Ptij6mA6SbKDsyCjkcQM/convert?cache=true&fit=crop&w=144&h=144"}, "published_date": "2016-11-03T14:13:04.751Z", "screenshot_hardware": "aplite", "screenshot_images": [{"144x168": "https://assets.getpebble.com/api/file/Ptij6mA6SbKDsyCjkcQM/convert?cache=true&fit=crop&w=144&h=168"}], "source": "", "title": "B/W with date", "type": "watchface", "uuid": "13371337-0e4b-4c5c-ab7b-c60f57c5dc4c", "website": ""}