{"author": "Dave Bowerman", "capabilities": [], "category_id": "528d3ef2dc7b5f580700000a", "category_name": "Faces", "category_color": "ffffff", "changelog": [{"version": "1.4", "published_date": "2015-12-02T05:35:26.581Z", "release_notes": "Updates for the display on Pebble Time Round"}, {"version": "1.3", "published_date": "2015-11-16T01:34:28.646Z", "release_notes": "Fixed and issue where the Temperature display would always revert to Celsius\r\nAdded ability to turn Day of the Week on / off via config settings"}, {"version": "1.2", "published_date": "2015-11-14T05:42:28.180Z", "release_notes": "Added the ability to show the local temperature.\r\nTurn on/off using the configuration page in the Pebble App."}, {"version": "1.1", "published_date": "2015-11-14T05:42:09.006Z", "release_notes": "Minor fixes.\r\nSupport for Pebble Time Round"}, {"version": "1.0", "published_date": "2015-10-12T23:43:04.863Z", "release_notes": "Version 1"}], "companions": {"ios": null, "android": null}, "compatibility": {"ios": {"supported": true, "min_js_version": -1}, "android": {"supported": true}, "aplite": {"supported": false, "firmware": {"major": 3}}, "basalt": {"supported": true, "firmware": {"major": 3}}, "chalk": {"supported": true, "firmware": {"major": 3}}, "diorite": {"supported": false, "firmware": {"major": 3}}, "emery": {"supported": true, "firmware": {"major": 3}}}, "created_at": "2015-10-12T23:29:03.816Z", "description": "A different take on Pebble's Tictoc Watchface. It includes the current Date which stays out of the way of the hands, and the 12 o'clock dot indicates if your Pebble is connected to your phone. Green connected, Red disconnected. The local temperature can also be displayed in either Celsius or Fahrenheit  by turning on the option in the settings.", "developer_id": "52f0446e1ac794fac8000eec", "header_images": "", "hearts": 92, "id": "561c423f74eabca44c00001e", "latest_release": {"id": "565e7fbca233778800000022", "js_md5": "34c8eb533f108f7e45ec824b28277a32", "js_version": -1, "pbw_file": "https://www.filepicker.io/api/file/4fwEaRQiQg2fSOlG2YOi", "published_date": "2015-12-02T05:35:26.581Z", "release_notes": "Updates for the display on Pebble Time Round", "version": "1.4"}, "links": {"add": "https://dev-portal.getpebble.com/api/applications/561c423f74eabca44c00001e/add", "remove": "https://dev-portal.getpebble.com/api/applications/561c423f74eabca44c00001e/remove", "add_heart": "https://dev-portal.getpebble.com/api/applications/561c423f74eabca44c00001e/add_heart", "remove_heart": "https://dev-portal.getpebble.com/api/applications/561c423f74eabca44c00001e/remove_heart", "add_flag": "https://dev-portal.getpebble.com/api/applications/561c423f74eabca44c00001e/flags/add", "remove_flag": "https://dev-portal.getpebble.com/api/applications/561c423f74eabca44c00001e/flags/remove", "share": "https://apps.getpebble.com/applications/561c423f74eabca44c00001e"}, "list_image": {"80x80": "https://assets.getpebble.com/api/file/LSI0gYdFQEaFpHp4SL87/convert?cache=true&fit=crop&w=80&h=80", "144x144": "https://assets.getpebble.com/api/file/LSI0gYdFQEaFpHp4SL87/convert?cache=true&fit=crop&w=144&h=144"}, "published_date": "2015-11-14T05:43:03.115Z", "screenshot_hardware": "basalt", "screenshot_images": [{"144x168": "https://assets.getpebble.com/api/file/LSI0gYdFQEaFpHp4SL87/convert?cache=true&fit=crop&w=144&h=168"}, {"144x168": "https://assets.getpebble.com/api/file/7fCjBcA5QlWqB5HZRyne/convert?cache=true&fit=crop&w=144&h=168"}], "source": "", "title": "TictocDate", "type": "watchface", "uuid": "076b4237-d34d-41ce-8ec3-9427c7c225f2", "website": ""}