{"author": "EpicLaith", "capabilities": [], "category_id": "528d3ef2dc7b5f580700000a", "category_name": "Faces", "category_color": "ffffff", "changelog": [{"version": "1.0", "published_date": "2014-10-08T11:33:12.786Z", "release_notes": ""}], "companions": {"ios": null, "android": null}, "compatibility": {"ios": {"supported": true, "min_js_version": -1}, "android": {"supported": true}, "aplite": {"supported": true, "firmware": {"major": 2}}, "basalt": {"supported": true, "firmware": {"major": 3}}, "chalk": {"supported": false, "firmware": {"major": 3}}, "diorite": {"supported": true, "firmware": {"major": 3}}, "emery": {"supported": true, "firmware": {"major": 3}}}, "created_at": "2014-10-08T11:32:45.358Z", "description": "An arabic watchface for everyone to download! I'm currently busy so I can't make custom watchfaces until July 2015. ", "developer_id": "53cbf761d7238308ee000062", "hearts": 6, "id": "543520dd32035c1e300001c5", "latest_release": {"id": "543520f372a84d558e0001b6", "js_version": -1, "pbw_file": "https://www.filepicker.io/api/file/YbSfG0eZQ4WbfJVivBLc", "published_date": "2014-10-08T11:33:12.786Z", "release_notes": "", "version": "1.0"}, "links": {"add": "https://dev-portal.getpebble.com/api/applications/543520dd32035c1e300001c5/add", "remove": "https://dev-portal.getpebble.com/api/applications/543520dd32035c1e300001c5/remove", "add_heart": "https://dev-portal.getpebble.com/api/applications/543520dd32035c1e300001c5/add_heart", "remove_heart": "https://dev-portal.getpebble.com/api/applications/543520dd32035c1e300001c5/remove_heart", "add_flag": "https://dev-portal.getpebble.com/api/applications/543520dd32035c1e300001c5/flags/add", "remove_flag": "https://dev-portal.getpebble.com/api/applications/543520dd32035c1e300001c5/flags/remove", "share": "https://apps.getpebble.com/applications/543520dd32035c1e300001c5"}, "list_image": {"80x80": "https://assets.getpebble.com/api/file/3CBAYZx3Q8qzWlbeKmns/convert?cache=true&fit=crop&w=80&h=80", "144x144": "https://assets.getpebble.com/api/file/3CBAYZx3Q8qzWlbeKmns/convert?cache=true&fit=crop&w=144&h=144"}, "published_date": "2014-10-08T11:33:17.879Z", "screenshot_hardware": "aplite", "screenshot_images": [{"144x168": "https://assets.getpebble.com/api/file/3CBAYZx3Q8qzWlbeKmns/convert?cache=true&fit=crop&w=144&h=168"}], "source": "", "title": "Arabizzie", "type": "watchface", "uuid": "13371337-bdc0-480b-afd4-ef6cde563789", "website": ""}