{"author": "Pete Stergion", "capabilities": [], "category_id": "528d3ef2dc7b5f580700000a", "category_name": "Faces", "category_color": "ffffff", "changelog": [{"version": "1.0.0", "published_date": "2014-03-05T16:57:32.439Z", "release_notes": ""}], "companions": {"ios": null, "android": null}, "compatibility": {"ios": {"supported": true, "min_js_version": -1}, "android": {"supported": true}, "aplite": {"supported": true, "firmware": {"major": 2}}, "basalt": {"supported": true, "firmware": {"major": 3}}, "chalk": {"supported": false, "firmware": {"major": 3}}, "diorite": {"supported": true, "firmware": {"major": 3}}, "emery": {"supported": true, "firmware": {"major": 3}}}, "created_at": "2014-03-05T16:57:15.281Z", "description": "Miami Marlins", "developer_id": "52b9eac2a1d2df34c40000cc", "hearts": 5, "id": "5317576b9315ec73d300047f", "latest_release": {"id": "53175776f655b6fef70005dd", "js_version": -1, "pbw_file": "https://www.filepicker.io/api/file/cqz61rxT3eFcGFAwxHcV", "published_date": "2014-03-05T16:57:32.439Z", "release_notes": "", "version": "1.0.0"}, "links": {"add": "https://dev-portal.getpebble.com/api/applications/5317576b9315ec73d300047f/add", "remove": "https://dev-portal.getpebble.com/api/applications/5317576b9315ec73d300047f/remove", "add_heart": "https://dev-portal.getpebble.com/api/applications/5317576b9315ec73d300047f/add_heart", "remove_heart": "https://dev-portal.getpebble.com/api/applications/5317576b9315ec73d300047f/remove_heart", "add_flag": "https://dev-portal.getpebble.com/api/applications/5317576b9315ec73d300047f/flags/add", "remove_flag": "https://dev-portal.getpebble.com/api/applications/5317576b9315ec73d300047f/flags/remove", "share": "https://apps.getpebble.com/applications/5317576b9315ec73d300047f"}, "list_image": {"80x80": "https://assets.getpebble.com/api/file/qEGEmCkYQ52Eo0Isbb9Q/convert?cache=true&fit=crop&w=80&h=80", "144x144": "https://assets.getpebble.com/api/file/qEGEmCkYQ52Eo0Isbb9Q/convert?cache=true&fit=crop&w=144&h=144"}, "published_date": "2014-03-05T16:57:35.459Z", "screenshot_hardware": "aplite", "screenshot_images": [{"144x168": "https://assets.getpebble.com/api/file/qEGEmCkYQ52Eo0Isbb9Q/convert?cache=true&fit=crop&w=144&h=168"}], "source": "", "title": "Miami Marlins", "type": "watchface", "uuid": "13371337-ce05-426e-a45b-b7447a645945", "website": ""}