{"author": "Maxim Babichev", "capabilities": [], "category_id": "528d3ef2dc7b5f580700000a", "category_name": "Faces", "category_color": "ffffff", "changelog": [{"version": "1.0", "published_date": "2014-12-20T18:56:16.840Z", "release_notes": "Version 1.0 (stable & pretty)"}], "companions": {"ios": null, "android": null}, "compatibility": {"ios": {"supported": true, "min_js_version": -1}, "android": {"supported": true}, "aplite": {"supported": true, "firmware": {"major": 2}}, "basalt": {"supported": true, "firmware": {"major": 3}}, "chalk": {"supported": false, "firmware": {"major": 3}}, "diorite": {"supported": true, "firmware": {"major": 3}}, "emery": {"supported": true, "firmware": {"major": 3}}}, "created_at": "2014-12-20T18:55:08.136Z", "description": "Wow\r\nSuch doge\r\nMuch simple\r\nVery watchface\r\n\r\nJust simple unofficial VK.com dog watchface. ", "developer_id": "532d086baadf559cb50000cd", "hearts": 10, "id": "5495c60cb48291499000012d", "latest_release": {"id": "5495c645b48291a306000091", "js_version": -1, "pbw_file": "https://www.filepicker.io/api/file/rOmKfudT5uTUIZ02PMYs", "published_date": "2014-12-20T18:56:16.840Z", "release_notes": "Version 1.0 (stable & pretty)", "version": "1.0"}, "links": {"add": "https://dev-portal.getpebble.com/api/applications/5495c60cb48291499000012d/add", "remove": "https://dev-portal.getpebble.com/api/applications/5495c60cb48291499000012d/remove", "add_heart": "https://dev-portal.getpebble.com/api/applications/5495c60cb48291499000012d/add_heart", "remove_heart": "https://dev-portal.getpebble.com/api/applications/5495c60cb48291499000012d/remove_heart", "add_flag": "https://dev-portal.getpebble.com/api/applications/5495c60cb48291499000012d/flags/add", "remove_flag": "https://dev-portal.getpebble.com/api/applications/5495c60cb48291499000012d/flags/remove", "share": "https://apps.getpebble.com/applications/5495c60cb48291499000012d"}, "list_image": {"80x80": "https://assets.getpebble.com/api/file/RLk2TyLTJabJARlH0LQf/convert?cache=true&fit=crop&w=80&h=80", "144x144": "https://assets.getpebble.com/api/file/RLk2TyLTJabJARlH0LQf/convert?cache=true&fit=crop&w=144&h=144"}, "published_date": "2014-12-20T18:56:30.656Z", "screenshot_hardware": "aplite", "screenshot_images": [{"144x168": "https://assets.getpebble.com/api/file/RLk2TyLTJabJARlH0LQf/convert?cache=true&fit=crop&w=144&h=168"}], "source": "", "title": "Vk Just Dog", "type": "watchface", "uuid": "13371337-98f0-4ab0-a8ea-ccd2cc57cd09", "website": "https://vk.com/max"}