{"author": "centuryglass", "capabilities": ["health"], "category_id": "528d3ef2dc7b5f580700000a", "category_name": "Faces", "category_color": "ffffff", "changelog": [{"version": "1.12", "published_date": "2016-03-06T00:06:07.026Z", "release_notes": "Added: themes, Pebble Health step count support, better time and date format options. "}, {"version": "1.01", "published_date": "2016-02-05T01:00:15.782Z", "release_notes": "Fixed problems with initial connection to the companion app."}, {"version": "1.0", "published_date": "2016-02-04T22:23:39.316Z", "release_notes": ""}], "companions": {"ios": null, "android": {"id": "56b3cf58c1aeb4560d000041", "icon": "https://www.filepicker.io/api/file/9Gnoe5kQkqKB8vM5h07w", "name": "EventPercent Watchface", "url": "https://play.google.com/store/apps/details?id=com.centuryglass.eventpercentwatchface", "required": true, "pebblekit_version": "3"}}, "compatibility": {"ios": {"supported": false}, "android": {"supported": true}, "aplite": {"supported": true, "firmware": {"major": 3}}, "basalt": {"supported": true, "firmware": {"major": 3}}, "chalk": {"supported": true, "firmware": {"major": 3}}, "diorite": {"supported": true, "firmware": {"major": 3}}, "emery": {"supported": true, "firmware": {"major": 3}}}, "created_at": "2016-01-27T05:11:06.324Z", "description": "EventPercent watchface shows you what percent of your calendar event has already passed, or how long you have until future events start.  Events are automatically fetched from calendars on your Android phone.  \r\n\r\nWeather, phone and Pebble battery percentage, and additional information are also displayed.  Information text at the top can display weather info, last detected location, unread SMS, or number of pages saved to Pocket.  Configuration options include calendar selection, color configuration, date and time formats, and more.", "developer_id": "5478fc07f94378516e000098", "header_images": "", "hearts": 56, "id": "56a8516af58e6beebf000019", "latest_release": {"id": "56db73d2eeaab1a8df000043", "js_version": -1, "pbw_file": "https://www.filepicker.io/api/file/tu9KlDImSB6F7aGpLr7X", "published_date": "2016-03-06T00:06:07.026Z", "release_notes": "Added: themes, Pebble Health step count support, better time and date format options. ", "version": "1.12"}, "links": {"add": "https://dev-portal.getpebble.com/api/applications/56a8516af58e6beebf000019/add", "remove": "https://dev-portal.getpebble.com/api/applications/56a8516af58e6beebf000019/remove", "add_heart": "https://dev-portal.getpebble.com/api/applications/56a8516af58e6beebf000019/add_heart", "remove_heart": "https://dev-portal.getpebble.com/api/applications/56a8516af58e6beebf000019/remove_heart", "add_flag": "https://dev-portal.getpebble.com/api/applications/56a8516af58e6beebf000019/flags/add", "remove_flag": "https://dev-portal.getpebble.com/api/applications/56a8516af58e6beebf000019/flags/remove", "share": "https://apps.getpebble.com/applications/56a8516af58e6beebf000019"}, "list_image": {"80x80": "https://assets.getpebble.com/api/file/h9lxx7iQa6y30dW11s9b/convert?cache=true&fit=crop&w=80&h=80", "144x144": "https://assets.getpebble.com/api/file/h9lxx7iQa6y30dW11s9b/convert?cache=true&fit=crop&w=144&h=144"}, "published_date": "2016-02-05T01:04:19.237Z", "screenshot_hardware": "basalt", "screenshot_images": [{"144x168": "https://assets.getpebble.com/api/file/h9lxx7iQa6y30dW11s9b/convert?cache=true&fit=crop&w=144&h=168"}, {"144x168": "https://assets.getpebble.com/api/file/1SoJNblQQtGaVUaoosf0/convert?cache=true&fit=crop&w=144&h=168"}, {"144x168": "https://assets.getpebble.com/api/file/H7c4xqo9T0Gk9DL4PUPC/convert?cache=true&fit=crop&w=144&h=168"}], "source": "https://github.com/centuryglass/eventwatch", "title": "EventPercent", "type": "watchface", "uuid": "aeb130aa-c1d5-43b1-aa55-4ae7c42eb9be", "website": ""}