{"data":[{"author":"craze","capabilities":["configurable"],"category_id":"5261a8fb3b773043d5000008","category_name":"Remotes","category_color":"fc4b4b","changelog":[{"version":"1.1","published_date":"2016-10-04T20:11:34.906Z","release_notes":"Fixed a bug where an unlocked door would not unlatch.\r\nAlso added an app icon for the pebble app picker"},{"version":"1.0","published_date":"2016-08-25T20:09:35.306Z","release_notes":"Initial Version"}],"companions":{"ios":null,"android":null},"compatibility":{"ios":{"supported":true,"min_js_version":-1},"android":{"supported":true},"aplite":{"supported":true,"firmware":{"major":3}},"basalt":{"supported":true,"firmware":{"major":3}},"chalk":{"supported":true,"firmware":{"major":3}},"diorite":{"supported":true,"firmware":{"major":3}},"emery":{"supported":true,"firmware":{"major":3}}},"created_at":"2016-08-12T20:47:38.643Z","description":"With this app you can manage your Nuki Smartlock. \r\n\r\nNote that a (software or hardware) Nuki Bridge is required for it to work.\r\n","developer_id":"556d4184d5f48469d600008c","header_images":"","hearts":10,"icon_image":{"28x28":"https://assets.getpebble.com/api/file/8WDEtMKVTaG3xw5vnu1H/convert?cache=true&fit=crop&w=28&h=28","48x48":"https://assets.getpebble.com/api/file/8WDEtMKVTaG3xw5vnu1H/convert?cache=true&fit=crop&w=48&h=48"},"id":"57ae35eabb85eded8e0002c8","latest_release":{"id":"57f40cee3c754a29050000d1","js_md5":"3ff86fe27502d34bb191bda698fc212d","js_version":-1,"pbw_file":"https://www.filepicker.io/api/file/b4kSWLjQgWlONz0gxeXC","published_date":"2016-10-04T20:11:34.906Z","release_notes":"Fixed a bug where an unlocked door would not unlatch.\r\nAlso added an app icon for the pebble app picker","version":"1.1"},"links":{"add":"https://dev-portal.getpebble.com/api/applications/57ae35eabb85eded8e0002c8/add","remove":"https://dev-portal.getpebble.com/api/applications/57ae35eabb85eded8e0002c8/remove","add_heart":"https://dev-portal.getpebble.com/api/applications/57ae35eabb85eded8e0002c8/add_heart","remove_heart":"https://dev-portal.getpebble.com/api/applications/57ae35eabb85eded8e0002c8/remove_heart","add_flag":"https://dev-portal.getpebble.com/api/applications/57ae35eabb85eded8e0002c8/flags/add","remove_flag":"https://dev-portal.getpebble.com/api/applications/57ae35eabb85eded8e0002c8/flags/remove","share":"https://apps.getpebble.com/applications/57ae35eabb85eded8e0002c8"},"list_image":{"80x80":"https://assets.getpebble.com/api/file/A5oOjgJYS2yzBz5vRtrM/convert?cache=true&fit=crop&w=80&h=80","144x144":"https://assets.getpebble.com/api/file/A5oOjgJYS2yzBz5vRtrM/convert?cache=true&fit=crop&w=144&h=144"},"published_date":"2016-08-25T20:36:19.495Z","screenshot_hardware":"basalt","screenshot_images":[{"144x168":"https://assets.getpebble.com/api/file/R2ZEycjGTwa9fEWRLHWc/convert?cache=true&fit=crop&w=144&h=168"},{"144x168":"https://assets.getpebble.com/api/file/250HYCPdTcuoEYKCw104/convert?cache=true&fit=crop&w=144&h=168"},{"144x168":"https://assets.getpebble.com/api/file/2sbZ7DAxSfC7QKhNgHFs/convert?cache=true&fit=crop&w=144&h=168"},{"144x168":"https://assets.getpebble.com/api/file/hSNDZCQTKajQaEdvs4p9/convert?cache=true&fit=crop&w=144&h=168"}],"source":"","title":"Nuki Bridge - Opener","type":"watchapp","uuid":"14384030-8e93-479d-bc73-5f80762bee85","website":""}],"limit":20,"offset":0,"links":{"nextPage":null}}